{"_type":"export","__export_format":4,"__export_date":"2024-07-16T19:58:05.733Z","__export_source":"insomnia.desktop.app:v8.4.5","resources":[{"_id":"req_70a05d40c813408cbaa1b21c7f7be311","parentId":"fld_83df3d0b81934ea3994955f9d34b9a59","modified":1721159031107,"created":1720830197761,"url":"{{ _.baseUrl }}/treatment/register","name":"Register","description":"","method":"POST","body":{"mimeType":"application/json","text":"{\n\t\"title\": \"Preciso de ajuda 2\", \n\t\"subject\": \"Não consigo sair do sistema\",\n\t\"type\": \"COMPLAINT\",\n\t\"sender\": {\n\t\t\"id\": \"27412c79-3537-46d8-9531-d1a6ea3ffc22\"\n\t},\n\t\"institute\":{\n\t\t\"id\": \"ff5a73b1-f91b-44f7-b958-08310eaedee3\"\n\t}\n}"},"parameters":[],"headers":[{"name":"Content-Type","value":"application/json"},{"name":"User-Agent","value":"insomnia/8.4.5"}],"authentication":{"type":"bearer","prefix":"Bearer","token":"{% response 'body', 'req_55f15999b83040098dd15800aeaa8754', 'b64::JC50b2tlbg==::46b', 'never', 60 %}"},"metaSortKey":-1719090558077,"isPrivate":false,"settingStoreCookies":true,"settingSendCookies":true,"settingDisableRenderRequestBody":false,"settingEncodeUrl":true,"settingRebuildPath":true,"settingFollowRedirects":"global","_type":"request"},{"_id":"fld_83df3d0b81934ea3994955f9d34b9a59","parentId":"wrk_545b2ac5d8bf4b1ab623fe857c5f25e8","modified":1720830197760,"created":1720830197760,"name":"Treatment","description":"","environment":{},"environmentPropertyOrder":null,"metaSortKey":-1719090538578,"_type":"request_group"},{"_id":"wrk_545b2ac5d8bf4b1ab623fe857c5f25e8","parentId":null,"modified":1720830197744,"created":1720830197744,"name":"Entregas 2.0","description":"","scope":"collection","_type":"workspace"},{"_id":"req_8f3314925cda40f69a2ad0488ef3bf05","parentId":"fld_83df3d0b81934ea3994955f9d34b9a59","modified":1720830197762,"created":1720830197762,"url":"{{ _.baseUrl }}/treatment/detail/094651c8-5aa0-4d50-bac9-4a5c513c36a8","name":"Detail","description":"","method":"GET","body":{},"parameters":[],"headers":[{"name":"User-Agent","value":"insomnia/8.4.5"}],"authentication":{"type":"bearer","prefix":"Bearer","token":"{% response 'body', 'req_de5e2bd3d4474e0495aa1d24b688272e', 'b64::JC50b2tlbg==::46b', 'never', 60 %}"},"metaSortKey":-1719090553149.5,"isPrivate":false,"settingStoreCookies":true,"settingSendCookies":true,"settingDisableRenderRequestBody":false,"settingEncodeUrl":true,"settingRebuildPath":true,"settingFollowRedirects":"global","_type":"request"},{"_id":"req_2e560a0ce181461b9029e5f1ce8d4b2c","parentId":"fld_83df3d0b81934ea3994955f9d34b9a59","modified":1721159043721,"created":1720830197765,"url":"{{ _.baseUrl }}/treatment/list/support/resolved","name":"Support Resolved","description":"","method":"GET","body":{},"parameters":[],"headers":[{"name":"User-Agent","value":"insomnia/8.4.5"}],"authentication":{"type":"bearer","prefix":"Bearer","token":"{% response 'body', 'req_55f15999b83040098dd15800aeaa8754', 'b64::JC50b2tlbg==::46b', 'never', 60 %}"},"metaSortKey":-1719090550685.75,"isPrivate":false,"settingStoreCookies":true,"settingSendCookies":true,"settingDisableRenderRequestBody":false,"settingEncodeUrl":true,"settingRebuildPath":true,"settingFollowRedirects":"global","_type":"request"},{"_id":"req_3a7e0a52948848f185182e9e9cddd701","parentId":"fld_83df3d0b81934ea3994955f9d34b9a59","modified":1721159052549,"created":1720830197765,"url":"{{ _.baseUrl }}/treatment/list/support/not-resolved","name":"Support Not Resolved","description":"","method":"GET","body":{},"parameters":[],"headers":[{"name":"User-Agent","value":"insomnia/8.4.5"}],"authentication":{"type":"bearer","prefix":"Bearer","token":"{% response 'body', 'req_55f15999b83040098dd15800aeaa8754', 'b64::JC50b2tlbg==::46b', 'never', 60 %}"},"metaSortKey":-1719090550377.7812,"isPrivate":false,"settingStoreCookies":true,"settingSendCookies":true,"settingDisableRenderRequestBody":false,"settingEncodeUrl":true,"settingRebuildPath":true,"settingFollowRedirects":"global","_type":"request"},{"_id":"req_3c7b27eb5ccd4d83ab0cbecab099feef","parentId":"fld_83df3d0b81934ea3994955f9d34b9a59","modified":1721159064343,"created":1720830197766,"url":"{{ _.baseUrl }}/treatment/list/complaint/resolved","name":"Complaint Resolved","description":"","method":"GET","body":{},"parameters":[],"headers":[{"name":"User-Agent","value":"insomnia/8.4.5"}],"authentication":{"type":"bearer","prefix":"Bearer","token":"{% response 'body', 'req_55f15999b83040098dd15800aeaa8754', 'b64::JC50b2tlbg==::46b', 'never', 60 %}"},"metaSortKey":-1719090550069.8125,"isPrivate":false,"settingStoreCookies":true,"settingSendCookies":true,"settingDisableRenderRequestBody":false,"settingEncodeUrl":true,"settingRebuildPath":true,"settingFollowRedirects":"global","_type":"request"},{"_id":"req_3ff857da62a544a998546619af313b5d","parentId":"fld_83df3d0b81934ea3994955f9d34b9a59","modified":1721159076156,"created":1720830197767,"url":"{{ _.baseUrl }}/treatment/list/complaint/not-resolved","name":"Complaint Not Resolved","description":"","method":"GET","body":{},"parameters":[],"headers":[{"name":"User-Agent","value":"insomnia/8.4.5"}],"authentication":{"type":"bearer","prefix":"Bearer","token":"{% response 'body', 'req_55f15999b83040098dd15800aeaa8754', 'b64::JC50b2tlbg==::46b', 'never', 60 %}"},"metaSortKey":-1719090549915.8281,"isPrivate":false,"settingStoreCookies":true,"settingSendCookies":true,"settingDisableRenderRequestBody":false,"settingEncodeUrl":true,"settingRebuildPath":true,"settingFollowRedirects":"global","_type":"request"},{"_id":"req_f674fa01807044039f5163d4a27602fb","parentId":"fld_83df3d0b81934ea3994955f9d34b9a59","modified":1721159090118,"created":1720830197768,"url":"{{ _.baseUrl }}/treatment/list/institute/resolved/61e53cc4-49e7-4e65-a654-8d05eaaa4985","name":"Complaint Resolved By Institute","description":"","method":"GET","body":{},"parameters":[],"headers":[{"name":"User-Agent","value":"insomnia/8.4.5"}],"authentication":{"type":"bearer","prefix":"Bearer","token":"{% response 'body', 'req_55f15999b83040098dd15800aeaa8754', 'b64::JC50b2tlbg==::46b', 'never', 60 %}"},"metaSortKey":-1719090549761.8438,"isPrivate":false,"settingStoreCookies":true,"settingSendCookies":true,"settingDisableRenderRequestBody":false,"settingEncodeUrl":true,"settingRebuildPath":true,"settingFollowRedirects":"global","_type":"request"},{"_id":"req_c1971c0af7e648cf9945297026f3eb86","parentId":"fld_83df3d0b81934ea3994955f9d34b9a59","modified":1721159098453,"created":1720830197769,"url":"{{ _.baseUrl }}/treatment/list/institute/not-resolved/61e53cc4-49e7-4e65-a654-8d05eaaa4985","name":"Complaint Not Resolved By Institute","description":"","method":"GET","body":{},"parameters":[],"headers":[{"name":"User-Agent","value":"insomnia/8.4.5"}],"authentication":{"type":"bearer","prefix":"Bearer","token":"{% response 'body', 'req_55f15999b83040098dd15800aeaa8754', 'b64::JC50b2tlbg==::46b', 'never', 60 %}"},"metaSortKey":-1719090548760.9453,"isPrivate":false,"settingStoreCookies":true,"settingSendCookies":true,"settingDisableRenderRequestBody":false,"settingEncodeUrl":true,"settingRebuildPath":true,"settingFollowRedirects":"global","_type":"request"},{"_id":"req_d0c64353f8094c06881a469b474574ca","parentId":"fld_83df3d0b81934ea3994955f9d34b9a59","modified":1721159109488,"created":1720830197770,"url":"{{ _.baseUrl }}/treatment/toggle/status-resolved/5045a7c4-aea3-4b7a-b0bd-04eccf1ae89c","name":"Toggle","description":"","method":"GET","body":{},"parameters":[],"headers":[{"name":"User-Agent","value":"insomnia/8.4.5"}],"authentication":{"type":"bearer","prefix":"Bearer","token":"{% response 'body', 'req_55f15999b83040098dd15800aeaa8754', 'b64::JC50b2tlbg==::46b', 'never', 60 %}"},"metaSortKey":-1719090548683.9531,"isPrivate":false,"settingStoreCookies":true,"settingSendCookies":true,"settingDisableRenderRequestBody":false,"settingEncodeUrl":true,"settingRebuildPath":true,"settingFollowRedirects":"global","_type":"request"},{"_id":"req_1238073c54084872add584ddc0223285","parentId":"fld_fb1caa55119f4d9fb223d88f772336d7","modified":1721152066227,"created":1720830239185,"url":"{{ _.baseUrl }}/institute/register","name":"Register","description":"","method":"POST","body":{"mimeType":"multipart/form-data","params":[{"name":"name","value":"Botique do Bolo","id":"pair_d8e13ed17a284d458a91a9579356e812","disabled":false},{"id":"pair_992803212e7745f4b3f04f515c41720b","name":"description","value":"Bons Bolos","description":"","disabled":false},{"id":"pair_2d5fb6d234ae46cd81f7a70d2fe67c03","name":"image","value":"","description":"","type":"file","fileName":"/home/lazaro/Imagens/entregas - public.png","multiline":true,"disabled":false},{"id":"pair_21967715f0644931a1390ba8e908c21a","name":"city","value":"Nova Cruz","description":"","disabled":false},{"id":"pair_b68ed3b79c144f74bfade5b4ecf47724","name":"longitude","value":"-35.289000","description":"","disabled":false},{"id":"pair_e1fbca6e6f144cfcadeb2ffa8e036f40","name":"latitude","value":"-6.614530","description":"","disabled":false},{"id":"pair_7875caf5f70c4d81abae2ccb3fad8869","name":"number","value":"17","description":"","disabled":false},{"id":"pair_b6537ce681674a28bafed053db8097f6","name":"complement","value":"Perto do Posto de Gasolina São Bras","description":"","disabled":false},{"id":"pair_a33feabddc974a659e83e6489291f8ca","name":"freight_cost_km","value":"2.6","description":"","disabled":false},{"id":"pair_6b1d0fc6ee5849b0a4361b937a2059f4","name":"whatsapp","value":"12345678921","description":"","disabled":false},{"id":"pair_7c613274050448e98b41dcac10bc9300","name":"user","value":"8a5680a2-faf2-4e2c-8410-58efaf946b59","description":"","type":"text","multiline":false,"disabled":false}]},"parameters":[],"headers":[{"name":"Content-Type","value":"multipart/form-data","id":"pair_cb66e58d187d4be095995d76087186a4","disabled":false},{"name":"User-Agent","value":"insomnia/8.4.5","id":"pair_5beced45c25044a293eda16adecced01","disabled":false}],"authentication":{"type":"bearer","prefix":"Bearer","token":"{% response 'body', 'req_55f15999b83040098dd15800aeaa8754', 'b64::JC50b2tlbg==::46b', 'never', 60 %}","disabled":false},"metaSortKey":-1719090558066.0625,"isPrivate":false,"settingStoreCookies":true,"settingSendCookies":true,"settingDisableRenderRequestBody":false,"settingEncodeUrl":true,"settingRebuildPath":true,"settingFollowRedirects":"global","_type":"request"},{"_id":"fld_fb1caa55119f4d9fb223d88f772336d7","parentId":"wrk_545b2ac5d8bf4b1ab623fe857c5f25e8","modified":1720830197771,"created":1720830197771,"name":"Institute","description":"","environment":{},"environmentPropertyOrder":null,"metaSortKey":-1719090538528,"_type":"request_group"},{"_id":"req_547ac4a23443424a9a4b4feb4078d3f7","parentId":"fld_fb1caa55119f4d9fb223d88f772336d7","modified":1721152155557,"created":1720880182075,"url":"{{ _.baseUrl }}/institute/update/a384d316-c8ef-481b-9c49-f6abbf96dde4","name":"Update","description":"","method":"PATCH","body":{"mimeType":"multipart/form-data","params":[{"name":"name","value":"Botique do Bolo JC","id":"pair_d8e13ed17a284d458a91a9579356e812","disabled":false},{"id":"pair_992803212e7745f4b3f04f515c41720b","name":"description","value":"Casa Boa","description":"","disabled":true},{"id":"pair_2d5fb6d234ae46cd81f7a70d2fe67c03","name":"image","value":"","description":"","type":"file","fileName":"/home/lazaro/Downloads/Frame 1.png","multiline":true,"disabled":true},{"id":"pair_21967715f0644931a1390ba8e908c21a","name":"city","value":"Jacaraú","description":"","disabled":true},{"id":"pair_b68ed3b79c144f74bfade5b4ecf47724","name":"longitude","value":"-35.289000","description":"","disabled":true},{"id":"pair_e1fbca6e6f144cfcadeb2ffa8e036f40","name":"latitude","value":"-6.614530","description":"","disabled":true},{"id":"pair_7875caf5f70c4d81abae2ccb3fad8869","name":"number","value":"16","description":"","disabled":true},{"id":"pair_b6537ce681674a28bafed053db8097f6","name":"complement","value":"Perto do Posto de Gasolina São Bras","description":"","disabled":true},{"id":"pair_a33feabddc974a659e83e6489291f8ca","name":"freight_cost_km","value":"2.6","description":"","disabled":true},{"id":"pair_6b1d0fc6ee5849b0a4361b937a2059f4","name":"whatsapp","value":"12345678912","description":"","disabled":true},{"id":"pair_7c613274050448e98b41dcac10bc9300","name":"user","value":"ac96a6c2-d569-43ae-b826-bf8452154066","description":"","type":"text","multiline":false,"disabled":true}]},"parameters":[],"headers":[{"name":"Content-Type","value":"multipart/form-data","id":"pair_cb66e58d187d4be095995d76087186a4","disabled":false},{"name":"User-Agent","value":"insomnia/8.4.5","id":"pair_5beced45c25044a293eda16adecced01","disabled":false}],"authentication":{"type":"bearer","prefix":"Bearer","token":"{% response 'body', 'req_55f15999b83040098dd15800aeaa8754', 'b64::JC50b2tlbg==::46b', 'never', 60 %}","disabled":false},"metaSortKey":-1719090558065.2812,"isPrivate":false,"settingStoreCookies":true,"settingSendCookies":true,"settingDisableRenderRequestBody":false,"settingEncodeUrl":true,"settingRebuildPath":true,"settingFollowRedirects":"global","_type":"request"},{"_id":"req_f7fc21c7a45240df90f3ce7e2e13227c","parentId":"fld_fb1caa55119f4d9fb223d88f772336d7","modified":1721152084522,"created":1720830197773,"url":"{{ _.baseUrl }}/institute/list/valid","name":"List Valid","description":"","method":"GET","body":{},"parameters":[],"headers":[{"name":"User-Agent","value":"insomnia/8.4.5"}],"authentication":{"type":"bearer","prefix":"Bearer","token":"{% response 'body', 'req_55f15999b83040098dd15800aeaa8754', 'b64::JC50b2tlbg==::46b', 'never', 60 %}","disabled":false},"metaSortKey":-1719090558027,"isPrivate":false,"settingStoreCookies":true,"settingSendCookies":true,"settingDisableRenderRequestBody":false,"settingEncodeUrl":true,"settingRebuildPath":true,"settingFollowRedirects":"global","_type":"request"},{"_id":"req_a172ad90f03c448bbf0bbcda24e54457","parentId":"fld_fb1caa55119f4d9fb223d88f772336d7","modified":1721159126242,"created":1720830197774,"url":"{{ _.baseUrl }}/institute/list/invalid","name":"List Invalid","description":"","method":"GET","body":{},"parameters":[],"headers":[{"name":"User-Agent","value":"insomnia/8.4.5"}],"authentication":{"type":"bearer","prefix":"Bearer","token":"{% response 'body', 'req_55f15999b83040098dd15800aeaa8754', 'b64::JC50b2tlbg==::46b', 'never', 60 %}"},"metaSortKey":-1719090558002,"isPrivate":false,"settingStoreCookies":true,"settingSendCookies":true,"settingDisableRenderRequestBody":false,"settingEncodeUrl":true,"settingRebuildPath":true,"settingFollowRedirects":"global","_type":"request"},{"_id":"req_258d775ecfae432bb7d12180ac7c81db","parentId":"fld_fb1caa55119f4d9fb223d88f772336d7","modified":1721159136010,"created":1720830197772,"url":"{{ _.baseUrl }}/institute/detail/ffb826f1-eb38-4172-8952-ae4c645c8c35","name":"Detail","description":"","method":"GET","body":{},"parameters":[],"headers":[{"name":"User-Agent","value":"insomnia/8.4.5"}],"authentication":{"type":"bearer","prefix":"Bearer","token":"{% response 'body', 'req_55f15999b83040098dd15800aeaa8754', 'b64::JC50b2tlbg==::46b', 'never', 60 %}"},"metaSortKey":-1719090557977,"isPrivate":false,"settingStoreCookies":true,"settingSendCookies":true,"settingDisableRenderRequestBody":false,"settingEncodeUrl":true,"settingRebuildPath":true,"settingFollowRedirects":"global","_type":"request"},{"_id":"req_49576fba592d49f6ba2b832a56001673","parentId":"fld_fb1caa55119f4d9fb223d88f772336d7","modified":1721159145414,"created":1720830197777,"url":"{{ _.baseUrl }}/institute/list/user/valid/2f166258-a24c-4b3e-8bbc-45fff25d2f5d ","name":"Valid by User","description":"","method":"GET","body":{},"parameters":[],"headers":[{"name":"User-Agent","value":"insomnia/8.4.5"}],"authentication":{"type":"bearer","prefix":"Bearer","token":"{% response 'body', 'req_55f15999b83040098dd15800aeaa8754', 'b64::JC50b2tlbg==::46b', 'never', 60 %}"},"metaSortKey":-1719090556770.125,"isPrivate":false,"settingStoreCookies":true,"settingSendCookies":true,"settingDisableRenderRequestBody":false,"settingEncodeUrl":true,"settingRebuildPath":true,"settingFollowRedirects":"global","_type":"request"},{"_id":"req_cc53c54314914104be61b9da7c86d0d6","parentId":"fld_fb1caa55119f4d9fb223d88f772336d7","modified":1721159154425,"created":1720830197778,"url":"{{ _.baseUrl }}/institute/list/user/invalid/10fc923b-5153-4822-8c8f-f28a1259ca8d","name":"Invalid by User","description":"","method":"GET","body":{},"parameters":[],"headers":[{"name":"User-Agent","value":"insomnia/8.4.5"}],"authentication":{"type":"bearer","prefix":"Bearer","token":"{% response 'body', 'req_55f15999b83040098dd15800aeaa8754', 'b64::JC50b2tlbg==::46b', 'never', 60 %}"},"metaSortKey":-1719090556166.6875,"isPrivate":false,"settingStoreCookies":true,"settingSendCookies":true,"settingDisableRenderRequestBody":false,"settingEncodeUrl":true,"settingRebuildPath":true,"settingFollowRedirects":"global","_type":"request"},{"_id":"req_d1eb91ec714e411192418752ec7448c6","parentId":"fld_fb1caa55119f4d9fb223d88f772336d7","modified":1721159163187,"created":1720830197776,"url":"{{ _.baseUrl }}/institute/toggle/activity/10fc923b-5153-4822-8c8f-f28a1259ca8d","name":"Toggle","description":"","method":"GET","body":{},"parameters":[],"headers":[{"name":"User-Agent","value":"insomnia/8.4.5"}],"authentication":{"type":"bearer","prefix":"Bearer","token":"{% response 'body', 'req_55f15999b83040098dd15800aeaa8754', 'b64::JC50b2tlbg==::46b', 'never', 60 %}"},"metaSortKey":-1719090555563.25,"isPrivate":false,"settingStoreCookies":true,"settingSendCookies":true,"settingDisableRenderRequestBody":false,"settingEncodeUrl":true,"settingRebuildPath":true,"settingFollowRedirects":"global","_type":"request"},{"_id":"req_66bf53cc92704fd196e6ae854434713b","parentId":"fld_d6c9c17ee84a4e588fc5a8a6cee5de4f","modified":1721152789484,"created":1720830197829,"url":"{{ _.baseUrl }}/product-item/register","name":"Register","description":"","method":"POST","body":{"mimeType":"application/json","text":"{\n\t\"quantity\": 2,\n\t\"product\": {\n\t\t\"id\": \"77aa3dfe-b124-4a7e-ae50-7769c545d525\"\n\t},\n\t\"user\": {\n\t\t\"id\": \"8a5680a2-faf2-4e2c-8410-58efaf946b59\"\n\t}\n}"},"parameters":[],"headers":[{"name":"Content-Type","value":"application/json"},{"name":"User-Agent","value":"insomnia/8.4.5"}],"authentication":{"type":"bearer","prefix":"Bearer","token":"{% response 'body', 'req_55f15999b83040098dd15800aeaa8754', 'b64::JC50b2tlbg==::46b', 'never', 60 %}"},"metaSortKey":-1719090558077,"isPrivate":false,"settingStoreCookies":true,"settingSendCookies":true,"settingDisableRenderRequestBody":false,"settingEncodeUrl":true,"settingRebuildPath":true,"settingFollowRedirects":"global","_type":"request"},{"_id":"fld_d6c9c17ee84a4e588fc5a8a6cee5de4f","parentId":"wrk_545b2ac5d8bf4b1ab623fe857c5f25e8","modified":1720830197829,"created":1720830197829,"name":"Product Item","description":"","environment":{},"environmentPropertyOrder":null,"metaSortKey":-1719090538521.75,"_type":"request_group"},{"_id":"req_0760e3ce6a954ff5a56ca9da01f9264f","parentId":"fld_d6c9c17ee84a4e588fc5a8a6cee5de4f","modified":1721159176052,"created":1720830197832,"url":"{{ _.baseUrl }}/product-item/update/88127f37-e2ed-4259-b38b-d95aefaf2aef","name":"Update","description":"","method":"PATCH","body":{"mimeType":"application/json","text":"{\n\t\"name\": \"Estab 2 do bom\" \n}"},"parameters":[],"headers":[{"name":"Content-Type","value":"application/json"},{"name":"User-Agent","value":"insomnia/8.4.5"}],"authentication":{"type":"bearer","prefix":"Bearer","token":"{% response 'body', 'req_55f15999b83040098dd15800aeaa8754', 'b64::JC50b2tlbg==::46b', 'never', 60 %}"},"metaSortKey":-1719090558052,"isPrivate":false,"settingStoreCookies":true,"settingSendCookies":true,"settingDisableRenderRequestBody":false,"settingEncodeUrl":true,"settingRebuildPath":true,"settingFollowRedirects":"global","_type":"request"},{"_id":"req_b9dd45c2f58a45aab62bfbd71e518347","parentId":"fld_d6c9c17ee84a4e588fc5a8a6cee5de4f","modified":1721159185386,"created":1720830197831,"url":"{{ _.baseUrl }}/product-item/detail/61f4cf95-88cb-4b1c-afa8-6055d01794df","name":"Detail","description":"","method":"GET","body":{},"parameters":[],"headers":[{"name":"User-Agent","value":"insomnia/8.4.5"},{"id":"pair_3346a740eb8c46bea894cffdc406e83f","name":"","value":"","description":""}],"authentication":{"type":"bearer","prefix":"Bearer","token":"{% response 'body', 'req_55f15999b83040098dd15800aeaa8754', 'b64::JC50b2tlbg==::46b', 'never', 60 %}"},"metaSortKey":-1719090557977,"isPrivate":false,"settingStoreCookies":true,"settingSendCookies":true,"settingDisableRenderRequestBody":false,"settingEncodeUrl":true,"settingRebuildPath":true,"settingFollowRedirects":"global","_type":"request"},{"_id":"req_383d30bc7b444fafbcbb4a4040451319","parentId":"fld_d6c9c17ee84a4e588fc5a8a6cee5de4f","modified":1721063774971,"created":1720830197833,"url":"{{ _.baseUrl }}/product-item/list/user/valid/8a5680a2-faf2-4e2c-8410-58efaf946b59","name":"Valid by User","description":"","method":"GET","body":{},"parameters":[],"headers":[{"name":"User-Agent","value":"insomnia/8.4.5"}],"authentication":{"type":"bearer","prefix":"Bearer","token":"{% response 'body', 'req_55f15999b83040098dd15800aeaa8754', 'b64::JC50b2tlbg==::46b', 'never', 60 %}"},"metaSortKey":-1719090557675.2812,"isPrivate":false,"settingStoreCookies":true,"settingSendCookies":true,"settingDisableRenderRequestBody":false,"settingEncodeUrl":true,"settingRebuildPath":true,"settingFollowRedirects":"global","_type":"request"},{"_id":"req_99aa7513b0a24d34b26f39b766b868da","parentId":"fld_d6c9c17ee84a4e588fc5a8a6cee5de4f","modified":1721159198695,"created":1720830197834,"url":"{{ _.baseUrl }}/product-item/delete/c2e0ce5b-098f-4c6a-9b46-2ea0c9b967d0","name":"Delete","description":"","method":"DELETE","body":{},"parameters":[],"headers":[{"name":"User-Agent","value":"insomnia/8.4.5"},{"id":"pair_3346a740eb8c46bea894cffdc406e83f","name":"","value":"","description":""}],"authentication":{"type":"bearer","prefix":"Bearer","token":"{% response 'body', 'req_55f15999b83040098dd15800aeaa8754', 'b64::JC50b2tlbg==::46b', 'never', 60 %}"},"metaSortKey":-1719090557373.5625,"isPrivate":false,"settingStoreCookies":true,"settingSendCookies":true,"settingDisableRenderRequestBody":false,"settingEncodeUrl":true,"settingRebuildPath":true,"settingFollowRedirects":"global","_type":"request"},{"_id":"req_745e4e6a7bd94ee392b2a31cbffc3008","parentId":"fld_22a2bec1793b43c2b9ef39a3706b7b10","modified":1721153010575,"created":1720830197851,"url":"{{ _.baseUrl }}/order-item/register","name":"Register","description":"","method":"POST","body":{"mimeType":"application/json","text":"{\n\t\"institute\": {\n\t\t\"id\":\"a384d316-c8ef-481b-9c49-f6abbf96dde4\"\n\t},\t\n\t\"distance\": 3,\n\t\"productItens\": [\n\t{\n\t\t\"id\": \"a0914f6e-2600-44a6-b12f-6837a23b0753\"\n\t},\n\t{\n\t\t\"id\": \"09f78f8a-80a4-4d2a-b786-b4a20c73f827\"\n\t},\n\t{\n\t\t\"id\": \"d28676d0-5b6c-4fb8-8e87-7034f4702212\"\n\t},\n\t{\n\t\t\"id\": \"32b41af5-4554-4257-83b2-aa51ec917c54\"\n\t},\n\t{\n\t\t\"id\": \"92ee963c-72ef-424e-979b-4ac8cb32fca8\"\n\t},\n\t{\n\t\t\"id\": \"1da8bb33-eb3c-4569-8664-dc91c099bc5b\"\n\t}\n]\n}"},"parameters":[],"headers":[{"name":"Content-Type","value":"application/json"},{"name":"User-Agent","value":"insomnia/8.4.5"}],"authentication":{"type":"bearer","prefix":"Bearer","token":"{% response 'body', 'req_55f15999b83040098dd15800aeaa8754', 'b64::JC50b2tlbg==::46b', 'never', 60 %}"},"metaSortKey":-1719090558077,"isPrivate":false,"settingStoreCookies":true,"settingSendCookies":true,"settingDisableRenderRequestBody":false,"settingEncodeUrl":true,"settingRebuildPath":true,"settingFollowRedirects":"global","_type":"request"},{"_id":"fld_22a2bec1793b43c2b9ef39a3706b7b10","parentId":"wrk_545b2ac5d8bf4b1ab623fe857c5f25e8","modified":1720830197850,"created":1720830197850,"name":"Order Item","description":"","environment":{},"environmentPropertyOrder":null,"metaSortKey":-1719090538520.1875,"_type":"request_group"},{"_id":"req_464861f9f5bf4da386d8f1745a442222","parentId":"fld_422692786769423fb8888bbe0711ac3c","modified":1721159212672,"created":1720830197853,"url":"{{ _.baseUrl }}/delivery/register","name":"Register","description":"","method":"POST","body":{"mimeType":"application/json","text":"{\n\t\"deliveryman\": {\n\t\t\"id\":\"19a9eadb-d190-488a-b1e5-f1648457b930\"\n\t},\n\t\"order\": {\n\t\t\"id\":\"d2f220dd-d01e-48a8-bc88-8ce2812da4bd\"\n\t}\n}"},"parameters":[],"headers":[{"name":"Content-Type","value":"application/json"},{"name":"User-Agent","value":"insomnia/8.4.5"}],"authentication":{"type":"bearer","prefix":"Bearer","token":"{% response 'body', 'req_55f15999b83040098dd15800aeaa8754', 'b64::JC50b2tlbg==::46b', 'never', 60 %}"},"metaSortKey":-1719090558077,"isPrivate":false,"settingStoreCookies":true,"settingSendCookies":true,"settingDisableRenderRequestBody":false,"settingEncodeUrl":true,"settingRebuildPath":true,"settingFollowRedirects":"global","_type":"request"},{"_id":"fld_422692786769423fb8888bbe0711ac3c","parentId":"wrk_545b2ac5d8bf4b1ab623fe857c5f25e8","modified":1720830197852,"created":1720830197852,"name":"Delivery","description":"","environment":{},"environmentPropertyOrder":null,"metaSortKey":-1719090538519.4062,"_type":"request_group"},{"_id":"req_4374a4d5df0f488db89a7fbff0d7e4da","parentId":"fld_422692786769423fb8888bbe0711ac3c","modified":1721159227278,"created":1720830197854,"url":"{{ _.baseUrl }}/delivery/list/deliveryman/sent/19a9eadb-d190-488a-b1e5-f1648457b930","name":"List Order Sent By Deliveryman","description":"","method":"GET","body":{},"parameters":[],"headers":[{"name":"User-Agent","value":"insomnia/8.4.5"}],"authentication":{"type":"bearer","prefix":"Bearer","token":"{% response 'body', 'req_55f15999b83040098dd15800aeaa8754', 'b64::JC50b2tlbg==::46b', 'never', 60 %}"},"metaSortKey":-1719090558064.5,"isPrivate":false,"settingStoreCookies":true,"settingSendCookies":true,"settingDisableRenderRequestBody":false,"settingEncodeUrl":true,"settingRebuildPath":true,"settingFollowRedirects":"global","_type":"request"},{"_id":"req_68481c4b3bcd4ed3821ed11f29336b4d","parentId":"fld_422692786769423fb8888bbe0711ac3c","modified":1721159235775,"created":1720830197855,"url":"{{ _.baseUrl }}/delivery/list/deliveryman/canceled/19a9eadb-d190-488a-b1e5-f1648457b930","name":"List Order Canceled By Deliveryman","description":"","method":"GET","body":{},"parameters":[],"headers":[{"name":"User-Agent","value":"insomnia/8.4.5"}],"authentication":{"type":"bearer","prefix":"Bearer","token":"{% response 'body', 'req_55f15999b83040098dd15800aeaa8754', 'b64::JC50b2tlbg==::46b', 'never', 60 %}"},"metaSortKey":-1719090558058.25,"isPrivate":false,"settingStoreCookies":true,"settingSendCookies":true,"settingDisableRenderRequestBody":false,"settingEncodeUrl":true,"settingRebuildPath":true,"settingFollowRedirects":"global","_type":"request"},{"_id":"req_40bf3524e67942678cfef00c64da2cac","parentId":"fld_422692786769423fb8888bbe0711ac3c","modified":1721159248799,"created":1720830197856,"url":"{{ _.baseUrl }}/delivery/list/deliveryman/delivered/19a9eadb-d190-488a-b1e5-f1648457b930","name":"List Order Delivered By Deliveryman","description":"","method":"GET","body":{},"parameters":[],"headers":[{"name":"User-Agent","value":"insomnia/8.4.5"}],"authentication":{"type":"bearer","prefix":"Bearer","token":"{% response 'body', 'req_55f15999b83040098dd15800aeaa8754', 'b64::JC50b2tlbg==::46b', 'never', 60 %}"},"metaSortKey":-1719090558055.125,"isPrivate":false,"settingStoreCookies":true,"settingSendCookies":true,"settingDisableRenderRequestBody":false,"settingEncodeUrl":true,"settingRebuildPath":true,"settingFollowRedirects":"global","_type":"request"},{"_id":"req_46ac77d6f38f42f3b230857a86826ebc","parentId":"fld_422692786769423fb8888bbe0711ac3c","modified":1721159257732,"created":1720830197857,"url":"{{ _.baseUrl }}/delivery/list/order/d2f220dd-d01e-48a8-bc88-8ce2812da4bd","name":"List Deliverymen by Order","description":"","method":"GET","body":{},"parameters":[],"headers":[{"name":"User-Agent","value":"insomnia/8.4.5"}],"authentication":{"type":"bearer","prefix":"Bearer","token":"{% response 'body', 'req_55f15999b83040098dd15800aeaa8754', 'b64::JC50b2tlbg==::46b', 'never', 60 %}"},"metaSortKey":-1719090558053.5625,"isPrivate":false,"settingStoreCookies":true,"settingSendCookies":true,"settingDisableRenderRequestBody":false,"settingEncodeUrl":true,"settingRebuildPath":true,"settingFollowRedirects":"global","_type":"request"},{"_id":"req_ade0e21d045f4f36a78c50c26e07c8e1","parentId":"fld_815362d3269f4ed99a131b021bca7aef","modified":1721135832147,"created":1720962791385,"url":"{{ _.baseUrl }}/order/api/list","name":"List Delivered","description":"","method":"GET","body":{},"parameters":[],"headers":[{"name":"User-Agent","value":"insomnia/8.4.5"}],"authentication":{},"metaSortKey":-1720962791385,"isPrivate":false,"settingStoreCookies":true,"settingSendCookies":true,"settingDisableRenderRequestBody":false,"settingEncodeUrl":true,"settingRebuildPath":true,"settingFollowRedirects":"global","_type":"request"},{"_id":"fld_815362d3269f4ed99a131b021bca7aef","parentId":"fld_4a24d355f3ef43bc9e322265456a1589","modified":1720962788377,"created":1720962788377,"name":"Api","description":"","environment":{},"environmentPropertyOrder":null,"metaSortKey":-1720962788377,"_type":"request_group"},{"_id":"fld_4a24d355f3ef43bc9e322265456a1589","parentId":"wrk_545b2ac5d8bf4b1ab623fe857c5f25e8","modified":1720830197835,"created":1720830197835,"name":"Order","description":"","environment":{},"environmentPropertyOrder":null,"metaSortKey":-1719090538518.625,"_type":"request_group"},{"_id":"req_093c50eedff842e39a0d8162b60ad355","parentId":"fld_4a24d355f3ef43bc9e322265456a1589","modified":1721159281188,"created":1720830197836,"url":"{{ _.baseUrl }}/order/detail/8bbd84ec-9b38-4a37-97b3-4b9943391c7e","name":"Detail","description":"","method":"GET","body":{},"parameters":[],"headers":[{"name":"User-Agent","value":"insomnia/8.4.5"},{"id":"pair_3346a740eb8c46bea894cffdc406e83f","name":"","value":"","description":""}],"authentication":{"type":"bearer","prefix":"Bearer","token":"{% response 'body', 'req_55f15999b83040098dd15800aeaa8754', 'b64::JC50b2tlbg==::46b', 'never', 60 %}"},"metaSortKey":-1719090557977,"isPrivate":false,"settingStoreCookies":true,"settingSendCookies":true,"settingDisableRenderRequestBody":false,"settingEncodeUrl":true,"settingRebuildPath":true,"settingFollowRedirects":"global","_type":"request"},{"_id":"req_acbbbf6b5e054e719d85bc5300ff6304","parentId":"fld_4a24d355f3ef43bc9e322265456a1589","modified":1721135904914,"created":1720830197838,"url":"{{ _.baseUrl }}/order/list/user/requested/8a5680a2-faf2-4e2c-8410-58efaf946b59","name":"List Requested by User","description":"","method":"GET","body":{},"parameters":[],"headers":[{"name":"User-Agent","value":"insomnia/8.4.5"}],"authentication":{"type":"bearer","prefix":"Bearer","token":"{% response 'body', 'req_55f15999b83040098dd15800aeaa8754', 'b64::JC50b2tlbg==::46b', 'never', 60 %}"},"metaSortKey":-1719090556770.125,"isPrivate":false,"settingStoreCookies":true,"settingSendCookies":true,"settingDisableRenderRequestBody":false,"settingEncodeUrl":true,"settingRebuildPath":true,"settingFollowRedirects":"global","_type":"request"},{"_id":"req_9439863c5d074a0f839537239f752cb8","parentId":"fld_4a24d355f3ef43bc9e322265456a1589","modified":1721159291150,"created":1720830197840,"url":"{{ _.baseUrl }}/order/list/user/sent/2f166258-a24c-4b3e-8bbc-45fff25d2f5d","name":"List Send by User","description":"","method":"GET","body":{},"parameters":[],"headers":[{"name":"User-Agent","value":"insomnia/8.4.5"}],"authentication":{"type":"bearer","prefix":"Bearer","token":"{% response 'body', 'req_55f15999b83040098dd15800aeaa8754', 'b64::JC50b2tlbg==::46b', 'never', 60 %}"},"metaSortKey":-1719090556468.4062,"isPrivate":false,"settingStoreCookies":true,"settingSendCookies":true,"settingDisableRenderRequestBody":false,"settingEncodeUrl":true,"settingRebuildPath":true,"settingFollowRedirects":"global","_type":"request"},{"_id":"req_b5c2d1ec40204b1194a1ed520a0dfd78","parentId":"fld_4a24d355f3ef43bc9e322265456a1589","modified":1721159299631,"created":1720830197841,"url":"{{ _.baseUrl }}/order/list/user/canceled/2f166258-a24c-4b3e-8bbc-45fff25d2f5d","name":"List Canceled by User","description":"","method":"GET","body":{},"parameters":[],"headers":[{"name":"User-Agent","value":"insomnia/8.4.5"}],"authentication":{"type":"bearer","prefix":"Bearer","token":"{% response 'body', 'req_55f15999b83040098dd15800aeaa8754', 'b64::JC50b2tlbg==::46b', 'never', 60 %}"},"metaSortKey":-1719090556317.5469,"isPrivate":false,"settingStoreCookies":true,"settingSendCookies":true,"settingDisableRenderRequestBody":false,"settingEncodeUrl":true,"settingRebuildPath":true,"settingFollowRedirects":"global","_type":"request"},{"_id":"req_41a3df8900bc444687546ab54ad87c9d","parentId":"fld_4a24d355f3ef43bc9e322265456a1589","modified":1721148255964,"created":1720830197842,"url":"{{ _.baseUrl }}/order/list/user/delivered/8a5680a2-faf2-4e2c-8410-58efaf946b59","name":"List Delivered by User","description":"","method":"GET","body":{},"parameters":[],"headers":[{"name":"User-Agent","value":"insomnia/8.4.5"}],"authentication":{"type":"bearer","prefix":"Bearer","token":"{% response 'body', 'req_55f15999b83040098dd15800aeaa8754', 'b64::JC50b2tlbg==::46b', 'never', 60 %}"},"metaSortKey":-1719090556242.1172,"isPrivate":false,"settingStoreCookies":true,"settingSendCookies":true,"settingDisableRenderRequestBody":false,"settingEncodeUrl":true,"settingRebuildPath":true,"settingFollowRedirects":"global","_type":"request"},{"_id":"req_1cac6c7257014c378fd81d8b8c5e9bce","parentId":"fld_4a24d355f3ef43bc9e322265456a1589","modified":1721148364474,"created":1720830197836,"url":"{{ _.baseUrl }}/order/status/canceled/1da28c89-d674-4257-8d1b-017352744312","name":"Cancel","description":"","method":"GET","body":{},"parameters":[],"headers":[{"name":"User-Agent","value":"insomnia/8.4.5"}],"authentication":{"type":"bearer","prefix":"Bearer","token":"{% response 'body', 'req_55f15999b83040098dd15800aeaa8754', 'b64::JC50b2tlbg==::46b', 'never', 60 %}"},"metaSortKey":-1719090555563.25,"isPrivate":false,"settingStoreCookies":true,"settingSendCookies":true,"settingDisableRenderRequestBody":false,"settingEncodeUrl":true,"settingRebuildPath":true,"settingFollowRedirects":"global","_type":"request"},{"_id":"req_ec9cb011657c4cfba500d37a81f63e6d","parentId":"fld_4a24d355f3ef43bc9e322265456a1589","modified":1721153354595,"created":1720830197839,"url":"{{ _.baseUrl }}/order/status/delivered/006c9555-f0dc-4757-97e0-56824a73fd0b","name":"Deliver","description":"","method":"GET","body":{},"parameters":[],"headers":[{"name":"User-Agent","value":"insomnia/8.4.5"}],"authentication":{"type":"bearer","prefix":"Bearer","token":"{% response 'body', 'req_55f15999b83040098dd15800aeaa8754', 'b64::JC50b2tlbg==::46b', 'never', 60 %}"},"metaSortKey":-1719090554356.375,"isPrivate":false,"settingStoreCookies":true,"settingSendCookies":true,"settingDisableRenderRequestBody":false,"settingEncodeUrl":true,"settingRebuildPath":true,"settingFollowRedirects":"global","_type":"request"},{"_id":"req_a13be3a8d53a457bad67a0949b1513cc","parentId":"fld_4a24d355f3ef43bc9e322265456a1589","modified":1721159316639,"created":1720830197849,"url":"{{ _.baseUrl }}/order/status/sent/d2f220dd-d01e-48a8-bc88-8ce2812da4bd","name":"Send","description":"","method":"GET","body":{},"parameters":[],"headers":[{"name":"User-Agent","value":"insomnia/8.4.5"}],"authentication":{"type":"bearer","prefix":"Bearer","token":"{% response 'body', 'req_55f15999b83040098dd15800aeaa8754', 'b64::JC50b2tlbg==::46b', 'never', 60 %}"},"metaSortKey":-1719090554306.375,"isPrivate":false,"settingStoreCookies":true,"settingSendCookies":true,"settingDisableRenderRequestBody":false,"settingEncodeUrl":true,"settingRebuildPath":true,"settingFollowRedirects":"global","_type":"request"},{"_id":"req_3a0bff92bcb8406da1bf009ddd27697a","parentId":"fld_4a24d355f3ef43bc9e322265456a1589","modified":1721159327217,"created":1720830197843,"url":"{{ _.baseUrl }}/order/list/institute/requested/a7c37109-e590-491e-9cc2-fd42e93b8705","name":"List Requested by Institute","description":"","method":"GET","body":{},"parameters":[],"headers":[{"name":"User-Agent","value":"insomnia/8.4.5"}],"authentication":{"type":"bearer","prefix":"Bearer","token":"{% response 'body', 'req_55f15999b83040098dd15800aeaa8754', 'b64::JC50b2tlbg==::46b', 'never', 60 %}"},"metaSortKey":-1719090554256.375,"isPrivate":false,"settingStoreCookies":true,"settingSendCookies":true,"settingDisableRenderRequestBody":false,"settingEncodeUrl":true,"settingRebuildPath":true,"settingFollowRedirects":"global","_type":"request"},{"_id":"req_4ee0d3eb3734413198040d53aa0054bd","parentId":"fld_4a24d355f3ef43bc9e322265456a1589","modified":1720830197844,"created":1720830197844,"url":"{{ _.baseUrl }}/order/list/institute/sent/a7c37109-e590-491e-9cc2-fd42e93b8705","name":"List Sent by Institute","description":"","method":"GET","body":{},"parameters":[],"headers":[{"name":"User-Agent","value":"insomnia/8.4.5"}],"authentication":{"type":"bearer","prefix":"Bearer","token":"{% response 'body', 'req_de5e2bd3d4474e0495aa1d24b688272e', 'b64::JC50b2tlbg==::46b', 'never', 60 %}"},"metaSortKey":-1719090553702.9375,"isPrivate":false,"settingStoreCookies":true,"settingSendCookies":true,"settingDisableRenderRequestBody":false,"settingEncodeUrl":true,"settingRebuildPath":true,"settingFollowRedirects":"global","_type":"request"},{"_id":"req_15022a30b51d41d4b2f55019547c1608","parentId":"fld_4a24d355f3ef43bc9e322265456a1589","modified":1721159341553,"created":1720830197846,"url":"{{ _.baseUrl }}/order/list/institute/canceled/76a200ae-4b22-4f3b-972c-035e26124a8d","name":"List Canceled by Institute","description":"","method":"GET","body":{},"parameters":[],"headers":[{"name":"User-Agent","value":"insomnia/8.4.5"}],"authentication":{"type":"bearer","prefix":"Bearer","token":"{% response 'body', 'req_55f15999b83040098dd15800aeaa8754', 'b64::JC50b2tlbg==::46b', 'never', 60 %}"},"metaSortKey":-1719090553426.2188,"isPrivate":false,"settingStoreCookies":true,"settingSendCookies":true,"settingDisableRenderRequestBody":false,"settingEncodeUrl":true,"settingRebuildPath":true,"settingFollowRedirects":"global","_type":"request"},{"_id":"req_5adae7f9cdde4dc182e734cea6d56596","parentId":"fld_4a24d355f3ef43bc9e322265456a1589","modified":1721159349337,"created":1720830197847,"url":"{{ _.baseUrl }}/order/list/institute/delivered/d2f220dd-d01e-48a8-bc88-8ce2812da4bd","name":"List Delivered by Institute","description":"","method":"GET","body":{},"parameters":[],"headers":[{"name":"User-Agent","value":"insomnia/8.4.5"}],"authentication":{"type":"bearer","prefix":"Bearer","token":"{% response 'body', 'req_55f15999b83040098dd15800aeaa8754', 'b64::JC50b2tlbg==::46b', 'never', 60 %}"},"metaSortKey":-1719090553287.8594,"isPrivate":false,"settingStoreCookies":true,"settingSendCookies":true,"settingDisableRenderRequestBody":false,"settingEncodeUrl":true,"settingRebuildPath":true,"settingFollowRedirects":"global","_type":"request"},{"_id":"req_692bbfec2f31402399def213888b8dc5","parentId":"fld_44e781159c664c0bbd4aa33b25af8761","modified":1721159363547,"created":1720830197793,"url":"{{ _.baseUrl }}/service/register","name":"Register","description":"","method":"POST","body":{"mimeType":"multipart/form-data","params":[{"name":"name","value":"Carpinteiro","id":"pair_0f4c9f70ed744d1584c873614a33db57","disabled":false},{"id":"pair_d0becca5787648b29e8f54d49e4cf8fc","name":"description","value":"Boa Carpintaria","description":"","disabled":false},{"id":"pair_634e4e06bdcb4ae3a2bbc3a8c3d3e150","name":"mode","value":"BY_SERVICE","description":""},{"id":"pair_1d4438c2ca664219a02087bb963641a7","name":"price","value":"90","description":""},{"id":"pair_d2294807c45d43e299523bb99e3406e0","name":"institute","value":"a384d316-c8ef-481b-9c49-f6abbf96dde4","description":""},{"id":"pair_d7527f3595dc44e1a8b42a2146d8f7c0","name":"image","value":"","description":"","type":"file","fileName":"/home/lazaro/Downloads/qrcode_media.tenor.com.png"}]},"parameters":[],"headers":[{"name":"Content-Type","value":"multipart/form-data"},{"name":"User-Agent","value":"insomnia/8.4.5"}],"authentication":{"type":"bearer","prefix":"Bearer","token":"{% response 'body', 'req_55f15999b83040098dd15800aeaa8754', 'b64::JC50b2tlbg==::46b', 'never', 60 %}"},"metaSortKey":-1719090558077,"isPrivate":false,"settingStoreCookies":true,"settingSendCookies":true,"settingDisableRenderRequestBody":false,"settingEncodeUrl":true,"settingRebuildPath":true,"settingFollowRedirects":"global","_type":"request"},{"_id":"fld_44e781159c664c0bbd4aa33b25af8761","parentId":"wrk_545b2ac5d8bf4b1ab623fe857c5f25e8","modified":1720830197792,"created":1720830197792,"name":"Service","description":"","environment":{},"environmentPropertyOrder":null,"metaSortKey":-1719090538515.5,"_type":"request_group"},{"_id":"req_f2e3027bfdd24de584c40adb296312fb","parentId":"fld_44e781159c664c0bbd4aa33b25af8761","modified":1721159370931,"created":1720908473127,"url":"{{ _.baseUrl }}/service/update/bd79fcb2-1d0b-401f-9989-74d638b66971","name":"Update","description":"","method":"PATCH","body":{"mimeType":"multipart/form-data","params":[{"name":"name","value":"Carpinteiro","id":"pair_0f4c9f70ed744d1584c873614a33db57","disabled":true},{"id":"pair_d0becca5787648b29e8f54d49e4cf8fc","name":"description","value":"Boa Carpintaria","description":"","disabled":true},{"id":"pair_634e4e06bdcb4ae3a2bbc3a8c3d3e150","name":"mode","value":"COMBINED","description":"","disabled":true},{"id":"pair_1d4438c2ca664219a02087bb963641a7","name":"price","value":"90","description":"","disabled":true},{"id":"pair_d2294807c45d43e299523bb99e3406e0","name":"institute","value":"a384d316-c8ef-481b-9c49-f6abbf96dde4","description":"","disabled":true},{"id":"pair_d7527f3595dc44e1a8b42a2146d8f7c0","name":"image","value":"","description":"","type":"file","fileName":"/home/lazaro/Downloads/qrcode_media.tenor.com.png","disabled":false}]},"parameters":[],"headers":[{"name":"Content-Type","value":"multipart/form-data"},{"name":"User-Agent","value":"insomnia/8.4.5"}],"authentication":{"type":"bearer","prefix":"Bearer","token":"{% response 'body', 'req_55f15999b83040098dd15800aeaa8754', 'b64::JC50b2tlbg==::46b', 'never', 60 %}"},"metaSortKey":-1719090558076.2188,"isPrivate":false,"settingStoreCookies":true,"settingSendCookies":true,"settingDisableRenderRequestBody":false,"settingEncodeUrl":true,"settingRebuildPath":true,"settingFollowRedirects":"global","_type":"request"},{"_id":"req_2830b6d40d9642e08ea2c2c08622f1f1","parentId":"fld_44e781159c664c0bbd4aa33b25af8761","modified":1721159378323,"created":1720830197795,"url":"{{ _.baseUrl }}/service/list/valid","name":"List Valid","description":"","method":"GET","body":{},"parameters":[],"headers":[{"name":"User-Agent","value":"insomnia/8.4.5"}],"authentication":{"type":"bearer","prefix":"Bearer","token":"{% response 'body', 'req_55f15999b83040098dd15800aeaa8754', 'b64::JC50b2tlbg==::46b', 'never', 60 %}"},"metaSortKey":-1719090558027,"isPrivate":false,"settingStoreCookies":true,"settingSendCookies":true,"settingDisableRenderRequestBody":false,"settingEncodeUrl":true,"settingRebuildPath":true,"settingFollowRedirects":"global","_type":"request"},{"_id":"req_63091575bee2454e809dcb3a406841ed","parentId":"fld_44e781159c664c0bbd4aa33b25af8761","modified":1721159387436,"created":1720830197797,"url":"{{ _.baseUrl }}/service/list/invalid","name":"List Invalid","description":"","method":"GET","body":{},"parameters":[],"headers":[{"name":"User-Agent","value":"insomnia/8.4.5"}],"authentication":{"type":"bearer","prefix":"Bearer","token":"{% response 'body', 'req_55f15999b83040098dd15800aeaa8754', 'b64::JC50b2tlbg==::46b', 'never', 60 %}"},"metaSortKey":-1719090558002,"isPrivate":false,"settingStoreCookies":true,"settingSendCookies":true,"settingDisableRenderRequestBody":false,"settingEncodeUrl":true,"settingRebuildPath":true,"settingFollowRedirects":"global","_type":"request"},{"_id":"req_6653c1e9ab9c4354a14214f62ffbfbfd","parentId":"fld_44e781159c664c0bbd4aa33b25af8761","modified":1721159396476,"created":1720830197794,"url":"{{ _.baseUrl }}/service/detail/fc76cb47-3e69-4e41-ac31-a80e002c854b","name":"Detail","description":"","method":"GET","body":{},"parameters":[],"headers":[{"name":"User-Agent","value":"insomnia/8.4.5"}],"authentication":{"type":"bearer","prefix":"Bearer","token":"{% response 'body', 'req_55f15999b83040098dd15800aeaa8754', 'b64::JC50b2tlbg==::46b', 'never', 60 %}"},"metaSortKey":-1719090557977,"isPrivate":false,"settingStoreCookies":true,"settingSendCookies":true,"settingDisableRenderRequestBody":false,"settingEncodeUrl":true,"settingRebuildPath":true,"settingFollowRedirects":"global","_type":"request"},{"_id":"req_1b833dfb679d40a2b1e20787db206b20","parentId":"fld_44e781159c664c0bbd4aa33b25af8761","modified":1721159404570,"created":1720830197800,"url":"{{ _.baseUrl }}/service/list/institute/valid/10fc923b-5153-4822-8c8f-f28a1259ca8d","name":"Valid by Institute","description":"","method":"GET","body":{},"parameters":[],"headers":[{"name":"User-Agent","value":"insomnia/8.4.5"}],"authentication":{"type":"bearer","prefix":"Bearer","token":"{% response 'body', 'req_55f15999b83040098dd15800aeaa8754', 'b64::JC50b2tlbg==::46b', 'never', 60 %}"},"metaSortKey":-1719090556770.125,"isPrivate":false,"settingStoreCookies":true,"settingSendCookies":true,"settingDisableRenderRequestBody":false,"settingEncodeUrl":true,"settingRebuildPath":true,"settingFollowRedirects":"global","_type":"request"},{"_id":"req_f788f17707db47bba6a9b204034fdcd2","parentId":"fld_44e781159c664c0bbd4aa33b25af8761","modified":1721159417034,"created":1720830197801,"url":"{{ _.baseUrl }}/service/list/institute/invalid/10fc923b-5153-4822-8c8f-f28a1259ca8d","name":"Invalid by Institute","description":"","method":"GET","body":{},"parameters":[],"headers":[{"name":"User-Agent","value":"insomnia/8.4.5"}],"authentication":{"type":"bearer","prefix":"Bearer","token":"{% response 'body', 'req_55f15999b83040098dd15800aeaa8754', 'b64::JC50b2tlbg==::46b', 'never', 60 %}"},"metaSortKey":-1719090556166.6875,"isPrivate":false,"settingStoreCookies":true,"settingSendCookies":true,"settingDisableRenderRequestBody":false,"settingEncodeUrl":true,"settingRebuildPath":true,"settingFollowRedirects":"global","_type":"request"},{"_id":"req_cf0a95b9bdcf469b975337e2b32d24f2","parentId":"fld_44e781159c664c0bbd4aa33b25af8761","modified":1721159429173,"created":1720830197799,"url":"{{ _.baseUrl }}/service/toggle/activity/bd79fcb2-1d0b-401f-9989-74d638b66971","name":"Toggle","description":"","method":"GET","body":{},"parameters":[],"headers":[{"name":"User-Agent","value":"insomnia/8.4.5"}],"authentication":{"type":"bearer","prefix":"Bearer","token":"{% response 'body', 'req_55f15999b83040098dd15800aeaa8754', 'b64::JC50b2tlbg==::46b', 'never', 60 %}"},"metaSortKey":-1719090555563.25,"isPrivate":false,"settingStoreCookies":true,"settingSendCookies":true,"settingDisableRenderRequestBody":false,"settingEncodeUrl":true,"settingRebuildPath":true,"settingFollowRedirects":"global","_type":"request"},{"_id":"req_36b59d2d3706425e96c40dcedd8db93e","parentId":"fld_f0061d0133e94488adc075ed8ac1aa8a","modified":1721152494249,"created":1720830197804,"url":"{{ _.baseUrl }}/product/register","name":"Register","description":"","method":"POST","body":{"mimeType":"multipart/form-data","params":[{"id":"pair_0b6c17921ece4f6493a21ca124c1ab42","name":"institute","value":"e08d03dc-ffd3-46e4-a4a7-817e84f6e5b3","description":""},{"id":"pair_af7df006ca064acf834644e6c5adf38d","name":"name","value":"Coxinha","description":""},{"id":"pair_3e882ff1a65f47d9bb55307740cd16b1","name":"category","value":"854c3f25-2c20-45fd-9ea0-898be6413251","description":""},{"id":"pair_0237354bcc3a428abb8a5ba1625c2983","name":"description","value":"Fatia de Bolo de chocolate 250g","description":""},{"id":"pair_ae552ebf2ce848c2a4de4e1803c55d95","name":"quantity","value":"9","description":""},{"id":"pair_0cf07096efe6443881d77a74a4ddad69","name":"price","value":"3.5","description":""},{"id":"pair_4053416c708b4253b3283d61a81449d1","name":"image","value":"","description":"","type":"file","multiline":true,"fileName":"/home/lazaro/Downloads/qrcode_media.tenor.com.png"}]},"parameters":[],"headers":[{"name":"Content-Type","value":"multipart/form-data"},{"name":"User-Agent","value":"insomnia/8.4.5"}],"authentication":{"type":"bearer","prefix":"Bearer","token":"{% response 'body', 'req_55f15999b83040098dd15800aeaa8754', 'b64::JC50b2tlbg==::46b', 'never', 60 %}"},"metaSortKey":-1719090558077,"isPrivate":false,"settingStoreCookies":true,"settingSendCookies":true,"settingDisableRenderRequestBody":false,"settingEncodeUrl":true,"settingRebuildPath":true,"settingFollowRedirects":"global","_type":"request"},{"_id":"fld_f0061d0133e94488adc075ed8ac1aa8a","parentId":"wrk_545b2ac5d8bf4b1ab623fe857c5f25e8","modified":1720890871798,"created":1720830197803,"name":"Product","description":"","environment":{},"environmentPropertyOrder":null,"metaSortKey":-1719090538509.25,"_type":"request_group"},{"_id":"req_153e22faa8a247a7819db354f10c91a5","parentId":"fld_f0061d0133e94488adc075ed8ac1aa8a","modified":1721063921189,"created":1720889144367,"url":"{{ _.baseUrl }}/product/update/10556d70-0c63-4ba6-8f46-ad67ae3ffa48","name":"Update","description":"","method":"PATCH","body":{"mimeType":"multipart/form-data","params":[{"id":"pair_0b6c17921ece4f6493a21ca124c1ab42","name":"institute","value":"05d12f97-982f-4ce5-bd95-9c6f58ae21ae","description":"","disabled":true},{"id":"pair_af7df006ca064acf834644e6c5adf38d","name":"name","value":"Pipoca","description":"","disabled":true},{"id":"pair_3e882ff1a65f47d9bb55307740cd16b1","name":"category","value":"65716b73-b619-4f6a-baa4-f23103afe63f","description":"","disabled":true},{"id":"pair_0237354bcc3a428abb8a5ba1625c2983","name":"description","value":"Pipoca Salgada Amantegada 500g","description":"","disabled":true},{"id":"pair_ae552ebf2ce848c2a4de4e1803c55d95","name":"quantity","value":"140","description":"","disabled":false},{"id":"pair_0cf07096efe6443881d77a74a4ddad69","name":"price","value":"2.5","description":"","disabled":true},{"id":"pair_4053416c708b4253b3283d61a81449d1","name":"image","value":"","description":"","type":"file","multiline":true,"fileName":"/home/lazaro/Imagens/entregas - public.png","disabled":true}]},"parameters":[],"headers":[{"name":"Content-Type","value":"multipart/form-data"},{"name":"User-Agent","value":"insomnia/8.4.5"}],"authentication":{"type":"bearer","prefix":"Bearer","token":"{% response 'body', 'req_55f15999b83040098dd15800aeaa8754', 'b64::JC50b2tlbg==::46b', 'never', 60 %}"},"metaSortKey":-1719090558073.875,"isPrivate":false,"settingStoreCookies":true,"settingSendCookies":true,"settingDisableRenderRequestBody":false,"settingEncodeUrl":true,"settingRebuildPath":true,"settingFollowRedirects":"global","_type":"request"},{"_id":"req_bfd1c04fce804c1a926f97b9c9a28d7a","parentId":"fld_f0061d0133e94488adc075ed8ac1aa8a","modified":1721148664965,"created":1720830197806,"url":"{{ _.baseUrl }}/product/list/valid","name":"List Valid","description":"","method":"GET","body":{},"parameters":[],"headers":[{"name":"User-Agent","value":"insomnia/8.4.5"}],"authentication":{"type":"bearer","prefix":"Bearer","token":"{% response 'body', 'req_55f15999b83040098dd15800aeaa8754', 'b64::JC50b2tlbg==::46b', 'never', 60 %}","disabled":false},"metaSortKey":-1719090558027,"isPrivate":false,"settingStoreCookies":true,"settingSendCookies":true,"settingDisableRenderRequestBody":false,"settingEncodeUrl":true,"settingRebuildPath":true,"settingFollowRedirects":"global","_type":"request"},{"_id":"req_945995daef074ed185031de4d708aa06","parentId":"fld_f0061d0133e94488adc075ed8ac1aa8a","modified":1721159447795,"created":1720830197807,"url":"{{ _.baseUrl }}/product/list/invalid","name":"List Invalid","description":"","method":"GET","body":{},"parameters":[],"headers":[{"name":"User-Agent","value":"insomnia/8.4.5"}],"authentication":{"type":"bearer","prefix":"Bearer","token":"{% response 'body', 'req_55f15999b83040098dd15800aeaa8754', 'b64::JC50b2tlbg==::46b', 'never', 60 %}"},"metaSortKey":-1719090558002,"isPrivate":false,"settingStoreCookies":true,"settingSendCookies":true,"settingDisableRenderRequestBody":false,"settingEncodeUrl":true,"settingRebuildPath":true,"settingFollowRedirects":"global","_type":"request"},{"_id":"req_78d6fbaba32842788f02ba0d65819bd0","parentId":"fld_f0061d0133e94488adc075ed8ac1aa8a","modified":1721159456923,"created":1720830197805,"url":"{{ _.baseUrl }}/product/detail/54287bfb-50a0-4afd-9340-0aff9a0e4189","name":"Detail","description":"","method":"GET","body":{},"parameters":[],"headers":[{"name":"User-Agent","value":"insomnia/8.4.5"}],"authentication":{"type":"bearer","prefix":"Bearer","token":"{% response 'body', 'req_55f15999b83040098dd15800aeaa8754', 'b64::JC50b2tlbg==::46b', 'never', 60 %}"},"metaSortKey":-1719090557977,"isPrivate":false,"settingStoreCookies":true,"settingSendCookies":true,"settingDisableRenderRequestBody":false,"settingEncodeUrl":true,"settingRebuildPath":true,"settingFollowRedirects":"global","_type":"request"},{"_id":"req_ce9202cab7604319b2a8ba8edfa87730","parentId":"fld_f0061d0133e94488adc075ed8ac1aa8a","modified":1721159467507,"created":1720830197812,"url":"{{ _.baseUrl }}/product/list/institute/valid/808dff47-db96-43bd-8d43-2b1bcb6fe61b","name":"Valid by Institute","description":"","method":"GET","body":{},"parameters":[],"headers":[{"name":"User-Agent","value":"insomnia/8.4.5"}],"authentication":{"type":"bearer","prefix":"Bearer","token":"{% response 'body', 'req_55f15999b83040098dd15800aeaa8754', 'b64::JC50b2tlbg==::46b', 'never', 60 %}"},"metaSortKey":-1719090556770.125,"isPrivate":false,"settingStoreCookies":true,"settingSendCookies":true,"settingDisableRenderRequestBody":false,"settingEncodeUrl":true,"settingRebuildPath":true,"settingFollowRedirects":"global","_type":"request"},{"_id":"req_688cf4d27d8f41f2ad010e14c136d24b","parentId":"fld_f0061d0133e94488adc075ed8ac1aa8a","modified":1721159475512,"created":1720830197814,"url":"{{ _.baseUrl }}/product/list/institute/invalid/808dff47-db96-43bd-8d43-2b1bcb6fe61b","name":"Invalid by Institute","description":"","method":"GET","body":{},"parameters":[],"headers":[{"name":"User-Agent","value":"insomnia/8.4.5"}],"authentication":{"type":"bearer","prefix":"Bearer","token":"{% response 'body', 'req_55f15999b83040098dd15800aeaa8754', 'b64::JC50b2tlbg==::46b', 'never', 60 %}"},"metaSortKey":-1719090556166.6875,"isPrivate":false,"settingStoreCookies":true,"settingSendCookies":true,"settingDisableRenderRequestBody":false,"settingEncodeUrl":true,"settingRebuildPath":true,"settingFollowRedirects":"global","_type":"request"},{"_id":"req_1802689abc2e479db4bb9841576998f3","parentId":"fld_f0061d0133e94488adc075ed8ac1aa8a","modified":1721159490330,"created":1720830197815,"url":"{{ _.baseUrl }}/product/list/product-category/valid/2d39c7c0-7c99-4756-8f52-dd631c11e96f","name":"Valid by Category","description":"","method":"GET","body":{},"parameters":[],"headers":[{"name":"User-Agent","value":"insomnia/8.4.5"}],"authentication":{"type":"bearer","prefix":"Bearer","token":"{% response 'body', 'req_55f15999b83040098dd15800aeaa8754', 'b64::JC50b2tlbg==::46b', 'never', 60 %}"},"metaSortKey":-1719090555864.9688,"isPrivate":false,"settingStoreCookies":true,"settingSendCookies":true,"settingDisableRenderRequestBody":false,"settingEncodeUrl":true,"settingRebuildPath":true,"settingFollowRedirects":"global","_type":"request"},{"_id":"req_3919142c67744f2fa376e76ad5822319","parentId":"fld_f0061d0133e94488adc075ed8ac1aa8a","modified":1721159497861,"created":1720830197816,"url":"{{ _.baseUrl }}/product/list/product-category/invalid/2d39c7c0-7c99-4756-8f52-dd631c11e96f","name":"Invalid by Category","description":"","method":"GET","body":{},"parameters":[],"headers":[{"name":"User-Agent","value":"insomnia/8.4.5"}],"authentication":{"type":"bearer","prefix":"Bearer","token":"{% response 'body', 'req_55f15999b83040098dd15800aeaa8754', 'b64::JC50b2tlbg==::46b', 'never', 60 %}"},"metaSortKey":-1719090555714.1094,"isPrivate":false,"settingStoreCookies":true,"settingSendCookies":true,"settingDisableRenderRequestBody":false,"settingEncodeUrl":true,"settingRebuildPath":true,"settingFollowRedirects":"global","_type":"request"},{"_id":"req_4f7fee6ffa29485d8aca059e113f76e0","parentId":"fld_f0061d0133e94488adc075ed8ac1aa8a","modified":1721159504681,"created":1720830197816,"url":"{{ _.baseUrl }}/product/list/institute/product-category/valid/808dff47-db96-43bd-8d43-2b1bcb6fe61b/2d39c7c0-7c99-4756-8f52-dd631c11e96f","name":"Valid by Category in Institute","description":"","method":"GET","body":{},"parameters":[],"headers":[{"name":"User-Agent","value":"insomnia/8.4.5"}],"authentication":{"type":"bearer","prefix":"Bearer","token":"{% response 'body', 'req_55f15999b83040098dd15800aeaa8754', 'b64::JC50b2tlbg==::46b', 'never', 60 %}"},"metaSortKey":-1719090555638.6797,"isPrivate":false,"settingStoreCookies":true,"settingSendCookies":true,"settingDisableRenderRequestBody":false,"settingEncodeUrl":true,"settingRebuildPath":true,"settingFollowRedirects":"global","_type":"request"},{"_id":"req_ef7dc1a1aa2e4b498e740e534aefd4c2","parentId":"fld_f0061d0133e94488adc075ed8ac1aa8a","modified":1721159514221,"created":1720830197810,"url":"{{ _.baseUrl }}/product/toggle/activity/935c62b2-7e57-4b2c-a647-37728561de28","name":"Toggle","description":"","method":"GET","body":{},"parameters":[],"headers":[{"name":"User-Agent","value":"insomnia/8.4.5"}],"authentication":{"type":"bearer","prefix":"Bearer","token":"{% response 'body', 'req_55f15999b83040098dd15800aeaa8754', 'b64::JC50b2tlbg==::46b', 'never', 60 %}"},"metaSortKey":-1719090555563.25,"isPrivate":false,"settingStoreCookies":true,"settingSendCookies":true,"settingDisableRenderRequestBody":false,"settingEncodeUrl":true,"settingRebuildPath":true,"settingFollowRedirects":"global","_type":"request"},{"_id":"req_4041cfbe293848aabde6ae698484f089","parentId":"fld_35e2f3801cf84945b78f11500bddf596","modified":1721159526721,"created":1720830197818,"url":"{{ _.baseUrl }}/deliveryman/register","name":"Register","description":"","method":"POST","body":{"mimeType":"multipart/form-data","params":[{"id":"pair_64353595d0cc4f03a9d5f0e15cf2ba45","name":"institute","value":"a384d316-c8ef-481b-9c49-f6abbf96dde4","description":""},{"id":"pair_d3efb142b4e34701988dd600bbb5e2ba","name":"user","value":"8a5680a2-faf2-4e2c-8410-58efaf946b59","description":""},{"id":"pair_45e9a5114a72467e915b3ca8792f9e96","name":"curriculum","value":"","description":"","type":"file","fileName":"/home/lazaro/Downloads/CV Padrão.pdf"}]},"parameters":[],"headers":[{"name":"Content-Type","value":"multipart/form-data"},{"name":"User-Agent","value":"insomnia/8.4.5"}],"authentication":{"type":"bearer","prefix":"Bearer","token":"{% response 'body', 'req_55f15999b83040098dd15800aeaa8754', 'b64::JC50b2tlbg==::46b', 'never', 60 %}"},"metaSortKey":-1719090558077,"isPrivate":false,"settingStoreCookies":true,"settingSendCookies":true,"settingDisableRenderRequestBody":false,"settingEncodeUrl":true,"settingRebuildPath":true,"settingFollowRedirects":"global","_type":"request"},{"_id":"fld_35e2f3801cf84945b78f11500bddf596","parentId":"wrk_545b2ac5d8bf4b1ab623fe857c5f25e8","modified":1720830197818,"created":1720830197818,"name":"Deliveryman","description":"","environment":{},"environmentPropertyOrder":null,"metaSortKey":-1719090538506.125,"_type":"request_group"},{"_id":"req_1f11165f28af409cbfee6b1840427dbf","parentId":"fld_35e2f3801cf84945b78f11500bddf596","modified":1721159534350,"created":1720894028049,"url":"{{ _.baseUrl }}/deliveryman/update/999d7ff2-4937-4bbc-9891-1d8307bb2ec0","name":"Update","description":"","method":"PATCH","body":{"mimeType":"multipart/form-data","params":[{"id":"pair_64353595d0cc4f03a9d5f0e15cf2ba45","name":"institute","value":"a384d316-c8ef-481b-9c49-f6abbf96dde4","description":"","disabled":true},{"id":"pair_d3efb142b4e34701988dd600bbb5e2ba","name":"user","value":"8a5680a2-faf2-4e2c-8410-58efaf946b59","description":"","disabled":true},{"id":"pair_45e9a5114a72467e915b3ca8792f9e96","name":"curriculum","value":"","description":"","type":"file","fileName":"/home/lazaro/Downloads/CV Backend Lázaro Alexandre - Alpha Software.pdf"}]},"parameters":[],"headers":[{"name":"Content-Type","value":"multipart/form-data"},{"name":"User-Agent","value":"insomnia/8.4.5"}],"authentication":{"type":"bearer","prefix":"Bearer","token":"{% response 'body', 'req_55f15999b83040098dd15800aeaa8754', 'b64::JC50b2tlbg==::46b', 'never', 60 %}"},"metaSortKey":-1719090558075.4375,"isPrivate":false,"settingStoreCookies":true,"settingSendCookies":true,"settingDisableRenderRequestBody":false,"settingEncodeUrl":true,"settingRebuildPath":true,"settingFollowRedirects":"global","_type":"request"},{"_id":"req_9f0cec0884a4430c9f0aef15140c0001","parentId":"fld_35e2f3801cf84945b78f11500bddf596","modified":1721159563229,"created":1720830197821,"url":"{{ _.baseUrl }}/deliveryman/list/valid","name":"List Valid","description":"","method":"GET","body":{},"parameters":[],"headers":[{"name":"User-Agent","value":"insomnia/8.4.5"}],"authentication":{"type":"bearer","prefix":"Bearer","token":"{% response 'body', 'req_55f15999b83040098dd15800aeaa8754', 'b64::JC50b2tlbg==::46b', 'never', 60 %}"},"metaSortKey":-1719090558027,"isPrivate":false,"settingStoreCookies":true,"settingSendCookies":true,"settingDisableRenderRequestBody":false,"settingEncodeUrl":true,"settingRebuildPath":true,"settingFollowRedirects":"global","_type":"request"},{"_id":"req_81611dd1e8794a458dec68d1c8a00cb4","parentId":"fld_35e2f3801cf84945b78f11500bddf596","modified":1721159571406,"created":1720830197821,"url":"{{ _.baseUrl }}/deliveryman/list/invalid","name":"List Invalid","description":"","method":"GET","body":{},"parameters":[],"headers":[{"name":"User-Agent","value":"insomnia/8.4.5"}],"authentication":{"type":"bearer","prefix":"Bearer","token":"{% response 'body', 'req_55f15999b83040098dd15800aeaa8754', 'b64::JC50b2tlbg==::46b', 'never', 60 %}"},"metaSortKey":-1719090558002,"isPrivate":false,"settingStoreCookies":true,"settingSendCookies":true,"settingDisableRenderRequestBody":false,"settingEncodeUrl":true,"settingRebuildPath":true,"settingFollowRedirects":"global","_type":"request"},{"_id":"req_aa4b93238b3a47e8a269312982c712f3","parentId":"fld_35e2f3801cf84945b78f11500bddf596","modified":1721159583089,"created":1720830197820,"url":"{{ _.baseUrl }}/deliveryman/detail/c8a97246-0481-4a9d-a528-4358c53b419f","name":"Detail","description":"","method":"GET","body":{},"parameters":[],"headers":[{"name":"User-Agent","value":"insomnia/8.4.5"}],"authentication":{"type":"bearer","prefix":"Bearer","token":"{% response 'body', 'req_55f15999b83040098dd15800aeaa8754', 'b64::JC50b2tlbg==::46b', 'never', 60 %}"},"metaSortKey":-1719090557977,"isPrivate":false,"settingStoreCookies":true,"settingSendCookies":true,"settingDisableRenderRequestBody":false,"settingEncodeUrl":true,"settingRebuildPath":true,"settingFollowRedirects":"global","_type":"request"},{"_id":"req_0f168b7f4f564b859f21aa50101559e9","parentId":"fld_35e2f3801cf84945b78f11500bddf596","modified":1721159596734,"created":1720830197824,"url":"{{ _.baseUrl }}/deliveryman/list/institute/valid/7d257702-6741-48c9-81e8-31af111fbc0b","name":"Valid by Institute","description":"","method":"GET","body":{},"parameters":[],"headers":[{"name":"User-Agent","value":"insomnia/8.4.5"}],"authentication":{"type":"bearer","prefix":"Bearer","token":"{% response 'body', 'req_55f15999b83040098dd15800aeaa8754', 'b64::JC50b2tlbg==::46b', 'never', 60 %}"},"metaSortKey":-1719090556770.125,"isPrivate":false,"settingStoreCookies":true,"settingSendCookies":true,"settingDisableRenderRequestBody":false,"settingEncodeUrl":true,"settingRebuildPath":true,"settingFollowRedirects":"global","_type":"request"},{"_id":"req_05daf8774ccf46d58f0e5e86f6f2f27b","parentId":"fld_35e2f3801cf84945b78f11500bddf596","modified":1721159604201,"created":1720830197825,"url":"{{ _.baseUrl }}/deliveryman/list/institute/invalid/7d257702-6741-48c9-81e8-31af111fbc0b","name":"Invalid by Institute","description":"","method":"GET","body":{},"parameters":[],"headers":[{"name":"User-Agent","value":"insomnia/8.4.5"}],"authentication":{"type":"bearer","prefix":"Bearer","token":"{% response 'body', 'req_55f15999b83040098dd15800aeaa8754', 'b64::JC50b2tlbg==::46b', 'never', 60 %}"},"metaSortKey":-1719090556166.6875,"isPrivate":false,"settingStoreCookies":true,"settingSendCookies":true,"settingDisableRenderRequestBody":false,"settingEncodeUrl":true,"settingRebuildPath":true,"settingFollowRedirects":"global","_type":"request"},{"_id":"req_287421fff5534fd0a1a1053adfad5880","parentId":"fld_35e2f3801cf84945b78f11500bddf596","modified":1721159615521,"created":1720830197826,"url":"{{ _.baseUrl }}/deliveryman/list/user/valid/27412c79-3537-46d8-9531-d1a6ea3ffc22","name":"Valid by User","description":"","method":"GET","body":{},"parameters":[],"headers":[{"name":"User-Agent","value":"insomnia/8.4.5"}],"authentication":{"type":"bearer","prefix":"Bearer","token":"{% response 'body', 'req_55f15999b83040098dd15800aeaa8754', 'b64::JC50b2tlbg==::46b', 'never', 60 %}"},"metaSortKey":-1719090555864.9688,"isPrivate":false,"settingStoreCookies":true,"settingSendCookies":true,"settingDisableRenderRequestBody":false,"settingEncodeUrl":true,"settingRebuildPath":true,"settingFollowRedirects":"global","_type":"request"},{"_id":"req_99ebd41e10734a4da2fd9b74b7c15e52","parentId":"fld_35e2f3801cf84945b78f11500bddf596","modified":1721159626091,"created":1720830197827,"url":"{{ _.baseUrl }}/deliveryman/list/user/invalid/2d39c7c0-7c99-4756-8f52-dd631c11e96f","name":"Invalid by User","description":"","method":"GET","body":{},"parameters":[],"headers":[{"name":"User-Agent","value":"insomnia/8.4.5"}],"authentication":{"type":"bearer","prefix":"Bearer","token":"{% response 'body', 'req_55f15999b83040098dd15800aeaa8754', 'b64::JC50b2tlbg==::46b', 'never', 60 %}"},"metaSortKey":-1719090555714.1094,"isPrivate":false,"settingStoreCookies":true,"settingSendCookies":true,"settingDisableRenderRequestBody":false,"settingEncodeUrl":true,"settingRebuildPath":true,"settingFollowRedirects":"global","_type":"request"},{"_id":"req_287db5981a7d4aeb9058f74058148eb2","parentId":"fld_35e2f3801cf84945b78f11500bddf596","modified":1721159634331,"created":1720830197823,"url":"{{ _.baseUrl }}/deliveryman/toggle/activity/f338bef1-0c68-4e28-a163-93e64955e3ac","name":"Toggle","description":"","method":"GET","body":{},"parameters":[],"headers":[{"name":"User-Agent","value":"insomnia/8.4.5"}],"authentication":{"type":"bearer","prefix":"Bearer","token":"{% response 'body', 'req_55f15999b83040098dd15800aeaa8754', 'b64::JC50b2tlbg==::46b', 'never', 60 %}"},"metaSortKey":-1719090555563.25,"isPrivate":false,"settingStoreCookies":true,"settingSendCookies":true,"settingDisableRenderRequestBody":false,"settingEncodeUrl":true,"settingRebuildPath":true,"settingFollowRedirects":"global","_type":"request"},{"_id":"req_aabd6029489a4d419e56ecdbf1cd41d1","parentId":"fld_15918daae0ff4fe493088e5ad34c5360","modified":1721159646547,"created":1720830197785,"url":"{{ _.baseUrl }}/product-category/register","name":"Register","description":"","method":"POST","body":{"mimeType":"application/json","text":"{\n\t\"name\": \"Salgados\"\n}"},"parameters":[],"headers":[{"name":"Content-Type","value":"application/json"},{"name":"User-Agent","value":"insomnia/8.4.5"}],"authentication":{"type":"bearer","prefix":"Bearer","token":"{% response 'body', 'req_55f15999b83040098dd15800aeaa8754', 'b64::JC50b2tlbg==::46b', 'never', 60 %}"},"metaSortKey":-1719090558077,"isPrivate":false,"settingStoreCookies":true,"settingSendCookies":true,"settingDisableRenderRequestBody":false,"settingEncodeUrl":true,"settingRebuildPath":true,"settingFollowRedirects":"global","_type":"request"},{"_id":"fld_15918daae0ff4fe493088e5ad34c5360","parentId":"wrk_545b2ac5d8bf4b1ab623fe857c5f25e8","modified":1720830197784,"created":1720830197784,"name":"Product Category","description":"","environment":{},"environmentPropertyOrder":null,"metaSortKey":-1719090538503,"_type":"request_group"},{"_id":"req_8dfaec1638354948a85eae7631b2db59","parentId":"fld_15918daae0ff4fe493088e5ad34c5360","modified":1721159655305,"created":1720830197789,"url":"{{ _.baseUrl }}/product-category/update/e47efb89-5d5f-4037-8b16-54a9aab816f7","name":"Update","description":"","method":"PATCH","body":{"mimeType":"application/json","text":"{\n\t\"name\": \"Gelados\" \n}"},"parameters":[],"headers":[{"name":"Content-Type","value":"application/json"},{"name":"User-Agent","value":"insomnia/8.4.5"}],"authentication":{"type":"bearer","prefix":"Bearer","token":"{% response 'body', 'req_55f15999b83040098dd15800aeaa8754', 'b64::JC50b2tlbg==::46b', 'never', 60 %}"},"metaSortKey":-1719090558052,"isPrivate":false,"settingStoreCookies":true,"settingSendCookies":true,"settingDisableRenderRequestBody":false,"settingEncodeUrl":true,"settingRebuildPath":true,"settingFollowRedirects":"global","_type":"request"},{"_id":"req_5a80fbc462f6418d90c1fc244ae9120a","parentId":"fld_15918daae0ff4fe493088e5ad34c5360","modified":1721159661803,"created":1720830197787,"url":"{{ _.baseUrl }}/product-category/list/valid","name":"List Valid","description":"","method":"GET","body":{},"parameters":[],"headers":[{"name":"User-Agent","value":"insomnia/8.4.5"}],"authentication":{"type":"bearer","prefix":"Bearer","token":"{% response 'body', 'req_55f15999b83040098dd15800aeaa8754', 'b64::JC50b2tlbg==::46b', 'never', 60 %}"},"metaSortKey":-1719090558027,"isPrivate":false,"settingStoreCookies":true,"settingSendCookies":true,"settingDisableRenderRequestBody":false,"settingEncodeUrl":true,"settingRebuildPath":true,"settingFollowRedirects":"global","_type":"request"},{"_id":"req_cf42e3488c1b4ccc9e77f2af04651757","parentId":"fld_15918daae0ff4fe493088e5ad34c5360","modified":1721159669313,"created":1720830197788,"url":"{{ _.baseUrl }}/product-category/list/invalid","name":"List Invalid","description":"","method":"GET","body":{},"parameters":[],"headers":[{"name":"User-Agent","value":"insomnia/8.4.5"}],"authentication":{"type":"bearer","prefix":"Bearer","token":"{% response 'body', 'req_55f15999b83040098dd15800aeaa8754', 'b64::JC50b2tlbg==::46b', 'never', 60 %}"},"metaSortKey":-1719090558002,"isPrivate":false,"settingStoreCookies":true,"settingSendCookies":true,"settingDisableRenderRequestBody":false,"settingEncodeUrl":true,"settingRebuildPath":true,"settingFollowRedirects":"global","_type":"request"},{"_id":"req_b1c900ca437b4c86a8fe0c1785371135","parentId":"fld_15918daae0ff4fe493088e5ad34c5360","modified":1721159676529,"created":1720830197786,"url":"{{ _.baseUrl }}/product-category/detail/e47efb89-5d5f-4037-8b16-54a9aab816f7","name":"Detail","description":"","method":"GET","body":{},"parameters":[],"headers":[{"name":"User-Agent","value":"insomnia/8.4.5"}],"authentication":{"type":"bearer","prefix":"Bearer","token":"{% response 'body', 'req_55f15999b83040098dd15800aeaa8754', 'b64::JC50b2tlbg==::46b', 'never', 60 %}"},"metaSortKey":-1719090557977,"isPrivate":false,"settingStoreCookies":true,"settingSendCookies":true,"settingDisableRenderRequestBody":false,"settingEncodeUrl":true,"settingRebuildPath":true,"settingFollowRedirects":"global","_type":"request"},{"_id":"req_84330b3810974a6dab85b0e4bccde8b6","parentId":"fld_15918daae0ff4fe493088e5ad34c5360","modified":1721159683891,"created":1720830197790,"url":"{{ _.baseUrl }}/product-category/toggle/activity/e47efb89-5d5f-4037-8b16-54a9aab816f7","name":"Toggle","description":"","method":"GET","body":{},"parameters":[],"headers":[{"name":"User-Agent","value":"insomnia/8.4.5"}],"authentication":{"type":"bearer","prefix":"Bearer","token":"{% response 'body', 'req_55f15999b83040098dd15800aeaa8754', 'b64::JC50b2tlbg==::46b', 'never', 60 %}"},"metaSortKey":-1719090555563.25,"isPrivate":false,"settingStoreCookies":true,"settingSendCookies":true,"settingDisableRenderRequestBody":false,"settingEncodeUrl":true,"settingRebuildPath":true,"settingFollowRedirects":"global","_type":"request"},{"_id":"req_ee1f1ec5c00b466d810e1b86d271da80","parentId":"fld_a6be8c223cba4610b448dd23c13db555","modified":1721159695671,"created":1720830197758,"url":"{{ _.baseUrl }}/user/update/user/27412c79-3537-46d8-9531-d1a6ea3ffc22","name":"Update","description":"","method":"PATCH","body":{"mimeType":"application/json","text":"{\n\t\"name\": \"Lázaro Alexandre\"\n}"},"parameters":[],"headers":[{"name":"Content-Type","value":"application/json"},{"name":"User-Agent","value":"insomnia/8.4.5"}],"authentication":{"type":"bearer","prefix":"Bearer","token":"{% response 'body', 'req_55f15999b83040098dd15800aeaa8754', 'b64::JC50b2tlbg==::46b', 'never', 60 %}"},"metaSortKey":-1719090577516,"isPrivate":false,"settingStoreCookies":true,"settingSendCookies":true,"settingDisableRenderRequestBody":false,"settingEncodeUrl":true,"settingRebuildPath":true,"settingFollowRedirects":"global","_type":"request"},{"_id":"fld_a6be8c223cba4610b448dd23c13db555","parentId":"wrk_545b2ac5d8bf4b1ab623fe857c5f25e8","modified":1720830197748,"created":1720830197748,"name":"User","description":"","environment":{},"environmentPropertyOrder":null,"metaSortKey":-1719090538478,"_type":"request_group"},{"_id":"req_0a587bbf89fb43228b7b38880b8a4b42","parentId":"fld_a6be8c223cba4610b448dd23c13db555","modified":1721159705096,"created":1720830197755,"url":"{{ _.baseUrl }}/user/suspense/account/27412c79-3537-46d8-9531-d1a6ea3ffc22","name":"Suspense Account","description":"","method":"GET","body":{},"parameters":[],"headers":[{"name":"User-Agent","value":"insomnia/8.4.5"}],"authentication":{"type":"bearer","prefix":"Bearer","token":"{% response 'body', 'req_55f15999b83040098dd15800aeaa8754', 'b64::JC50b2tlbg==::46b', 'never', 60 %}"},"metaSortKey":-1719090577416,"isPrivate":false,"settingStoreCookies":true,"settingSendCookies":true,"settingDisableRenderRequestBody":false,"settingEncodeUrl":true,"settingRebuildPath":true,"settingFollowRedirects":"global","_type":"request"},{"_id":"req_a75137edefed400886282566d3784155","parentId":"fld_a6be8c223cba4610b448dd23c13db555","modified":1721159711826,"created":1720830197759,"url":"{{ _.baseUrl }}/user/close/account/27412c79-3537-46d8-9531-d1a6ea3ffc22","name":"Close Account","description":"","method":"GET","body":{},"parameters":[],"headers":[{"name":"User-Agent","value":"insomnia/8.4.5"}],"authentication":{"type":"bearer","prefix":"Bearer","token":"{% response 'body', 'req_55f15999b83040098dd15800aeaa8754', 'b64::JC50b2tlbg==::46b', 'never', 60 %}"},"metaSortKey":-1719090577409.75,"isPrivate":false,"settingStoreCookies":true,"settingSendCookies":true,"settingDisableRenderRequestBody":false,"settingEncodeUrl":true,"settingRebuildPath":true,"settingFollowRedirects":"global","_type":"request"},{"_id":"req_7b1786212caf4bea8f8a7f35ea3a77f0","parentId":"fld_a6be8c223cba4610b448dd23c13db555","modified":1721159722592,"created":1720830197757,"url":"{{ _.baseUrl }}/user/update/role/27412c79-3537-46d8-9531-d1a6ea3ffc22","name":"Update Role","description":"","method":"GET","body":{},"parameters":[],"headers":[{"name":"User-Agent","value":"insomnia/8.4.5"}],"authentication":{"type":"bearer","prefix":"Bearer","token":"{% response 'body', 'req_55f15999b83040098dd15800aeaa8754', 'b64::JC50b2tlbg==::46b', 'never', 60 %}"},"metaSortKey":-1719090577403.5,"isPrivate":false,"settingStoreCookies":true,"settingSendCookies":true,"settingDisableRenderRequestBody":false,"settingEncodeUrl":true,"settingRebuildPath":true,"settingFollowRedirects":"global","_type":"request"},{"_id":"req_815354e95c7b4e1fa29cde17ac48a709","parentId":"fld_a6be8c223cba4610b448dd23c13db555","modified":1721159733568,"created":1720830197756,"url":"{{ _.baseUrl }}/user/reactivate/account/27412c79-3537-46d8-9531-d1a6ea3ffc22","name":"Reactive Account","description":"","method":"GET","body":{},"parameters":[],"headers":[{"name":"User-Agent","value":"insomnia/8.4.5"}],"authentication":{"type":"bearer","prefix":"Bearer","token":"{% response 'body', 'req_55f15999b83040098dd15800aeaa8754', 'b64::JC50b2tlbg==::46b', 'never', 60 %}"},"metaSortKey":-1719090577366,"isPrivate":false,"settingStoreCookies":true,"settingSendCookies":true,"settingDisableRenderRequestBody":false,"settingEncodeUrl":true,"settingRebuildPath":true,"settingFollowRedirects":"global","_type":"request"},{"_id":"req_09c486c488e04fe1b4e81e62534f4e05","parentId":"fld_a6be8c223cba4610b448dd23c13db555","modified":1721159741196,"created":1720830197751,"url":"{{ _.baseUrl }}/user/detail/5417c83f-9698-4e6e-9f42-918b08b08e2e","name":"Detail","description":"","method":"GET","body":{},"parameters":[],"headers":[{"name":"User-Agent","value":"insomnia/8.4.5"}],"authentication":{"type":"bearer","prefix":"Bearer","token":"{% response 'body', 'req_55f15999b83040098dd15800aeaa8754', 'b64::JC50b2tlbg==::46b', 'never', 60 %}"},"metaSortKey":-1719090577316,"isPrivate":false,"settingStoreCookies":true,"settingSendCookies":true,"settingDisableRenderRequestBody":false,"settingEncodeUrl":true,"settingRebuildPath":true,"settingFollowRedirects":"global","_type":"request"},{"_id":"req_eb8dfc629c8542bc86054f0e0864ad25","parentId":"fld_a6be8c223cba4610b448dd23c13db555","modified":1721159756697,"created":1720830197752,"url":"{{ _.baseUrl }}/user/list/valid","name":"List Valid","description":"","method":"GET","body":{},"parameters":[],"headers":[{"name":"User-Agent","value":"insomnia/8.4.5"}],"authentication":{"type":"bearer","prefix":"Bearer","token":"{% response 'body', 'req_55f15999b83040098dd15800aeaa8754', 'b64::JC50b2tlbg==::46b', 'never', 60 %}","disabled":false},"metaSortKey":-1719090577216,"isPrivate":false,"settingStoreCookies":true,"settingSendCookies":true,"settingDisableRenderRequestBody":false,"settingEncodeUrl":true,"settingRebuildPath":true,"settingFollowRedirects":"global","_type":"request"},{"_id":"req_0615407022c8475bbbd75338bb4733ab","parentId":"fld_a6be8c223cba4610b448dd23c13db555","modified":1721159765759,"created":1720830197753,"url":"{{ _.baseUrl }}/user/list/invalid","name":"List Invalid","description":"","method":"GET","body":{},"parameters":[],"headers":[{"name":"User-Agent","value":"insomnia/8.4.5"}],"authentication":{"type":"bearer","prefix":"Bearer","token":"{% response 'body', 'req_55f15999b83040098dd15800aeaa8754', 'b64::JC50b2tlbg==::46b', 'never', 60 %}"},"metaSortKey":-1719090577191,"isPrivate":false,"settingStoreCookies":true,"settingSendCookies":true,"settingDisableRenderRequestBody":false,"settingEncodeUrl":true,"settingRebuildPath":true,"settingFollowRedirects":"global","_type":"request"},{"_id":"req_541918b7703640b293f7729abad44f3a","parentId":"fld_a6be8c223cba4610b448dd23c13db555","modified":1721159773697,"created":1720830197754,"url":"{{ _.baseUrl }}/user/list/admin/invalid","name":"List Actived","description":"","method":"GET","body":{},"parameters":[],"headers":[{"name":"User-Agent","value":"insomnia/8.4.5"}],"authentication":{"type":"bearer","prefix":"Bearer","token":"{% response 'body', 'req_55f15999b83040098dd15800aeaa8754', 'b64::JC50b2tlbg==::46b', 'never', 60 %}"},"metaSortKey":-1719090577178.5,"isPrivate":false,"settingStoreCookies":true,"settingSendCookies":true,"settingDisableRenderRequestBody":false,"settingEncodeUrl":true,"settingRebuildPath":true,"settingFollowRedirects":"global","_type":"request"},{"_id":"req_695c254001424d7988525b1f7337df97","parentId":"fld_a6be8c223cba4610b448dd23c13db555","modified":1720893574139,"created":1720830197750,"url":"{{ _.baseUrl }}/user/validate/account/8a5680a2-faf2-4e2c-8410-58efaf946b59","name":"Validate","description":"","method":"GET","body":{},"parameters":[],"headers":[{"name":"User-Agent","value":"insomnia/8.4.5"}],"authentication":{},"metaSortKey":-1719090577166,"isPrivate":false,"settingStoreCookies":true,"settingSendCookies":true,"settingDisableRenderRequestBody":false,"settingEncodeUrl":true,"settingRebuildPath":true,"settingFollowRedirects":"global","_type":"request"},{"_id":"req_d8581087d8614fe087cee534b2e87a1f","parentId":"fld_a6be8c223cba4610b448dd23c13db555","modified":1720830197750,"created":1720830197750,"url":"{{ _.baseUrl }}/user/register","name":"Register","description":"","method":"POST","body":{"mimeType":"application/json","text":"{\n\t\"name\": \"lazaro\",\n\t\"email\": \"lazaroalexandre2002@gmail.com\"\n}"},"parameters":[],"headers":[{"name":"Content-Type","value":"application/json"},{"name":"User-Agent","value":"insomnia/8.4.5"}],"authentication":{},"metaSortKey":-1719090558077,"isPrivate":false,"settingStoreCookies":true,"settingSendCookies":true,"settingDisableRenderRequestBody":false,"settingEncodeUrl":true,"settingRebuildPath":true,"settingFollowRedirects":"global","_type":"request"},{"_id":"req_55f15999b83040098dd15800aeaa8754","parentId":"fld_a6be8c223cba4610b448dd23c13db555","modified":1720830197748,"created":1720830197748,"url":"{{ _.baseUrl }}/user/login","name":"Login","description":"","method":"POST","body":{"mimeType":"application/json","text":"{\n\t\"email\": \"lazaroalexandre2002@gmail.com\"\n}"},"parameters":[],"headers":[{"name":"Content-Type","value":"application/json"},{"name":"User-Agent","value":"insomnia/8.4.5"}],"authentication":{},"metaSortKey":-1719090548222,"isPrivate":false,"settingStoreCookies":true,"settingSendCookies":true,"settingDisableRenderRequestBody":false,"settingEncodeUrl":true,"settingRebuildPath":true,"settingFollowRedirects":"global","_type":"request"},{"_id":"env_02640e01d72d4361946c0980fa6e3bc9","parentId":"wrk_545b2ac5d8bf4b1ab623fe857c5f25e8","modified":1720830197745,"created":1720830197745,"name":"Base Environment","data":{"baseUrl":"http://localhost:8080"},"dataPropertyOrder":{"&":["baseUrl"]},"color":null,"isPrivate":false,"metaSortKey":1719090520473,"_type":"environment"},{"_id":"jar_2e2e56ec3d8c436881bf0d97ca1a4637","parentId":"wrk_545b2ac5d8bf4b1ab623fe857c5f25e8","modified":1720830197746,"created":1720830197746,"name":"Default Jar","cookies":[{"key":"JSESSIONID","value":"4671CFB81D51AD8F3970663042ED7581","domain":"localhost","path":"/","httpOnly":true,"hostOnly":true,"creation":"2024-07-12T18:09:40.311Z","lastAccessed":"2024-07-12T18:09:40.311Z","id":"9ae07b24-7973-4b0a-91e3-033c9c21b33f"}],"_type":"cookie_jar"},{"_id":"spc_afc3276524a74e33a3a1a502b5d32a07","parentId":"wrk_545b2ac5d8bf4b1ab623fe857c5f25e8","modified":1720830197863,"created":1720830197862,"fileName":"Entregas 2.0","contents":"","contentType":"yaml","_type":"api_spec"}]}